rival_regions_wrapper/__init__.py
rival_regions_wrapper/api.py
rival_regions_wrapper/authentication_handler.py
rival_regions_wrapper/browser.py
rival_regions_wrapper/cookie_handler.py
rival_regions_wrapper/exceptions.py
rival_regions_wrapper/login_methods.py
rival_regions_wrapper/middleware.py
rival_regions_wrapper/util.py
rival_regions_wrapper/wrapper/__init__.py
rival_regions_wrapper/wrapper/abstract_wrapper.py
rival_regions_wrapper/wrapper/article.py
rival_regions_wrapper/wrapper/conference.py
rival_regions_wrapper/wrapper/craft.py
rival_regions_wrapper/wrapper/language_chat.py
rival_regions_wrapper/wrapper/market.py
rival_regions_wrapper/wrapper/overview.py
rival_regions_wrapper/wrapper/perks.py
rival_regions_wrapper/wrapper/profile.py
rival_regions_wrapper/wrapper/resource_state.py
rival_regions_wrapper/wrapper/storage.py
rival_regions_wrapper/wrapper/war.py
rival_regions_wrapper/wrapper/work.py
rival_regions_wrapper-1.3.3.dist-info/LICENSE
rival_regions_wrapper-1.3.3.dist-info/METADATA
rival_regions_wrapper-1.3.3.dist-info/WHEEL
rival_regions_wrapper-1.3.3.dist-info/top_level.txt
rival_regions_wrapper-1.3.3.dist-info/RECORD
