Metadata-Version: 2.1
Name: rival-regions-wrapper
Version: 1.3.3
Summary: Rival Regions API wrapper
Home-page: https://github.com/joostsijm/rival_regions_wrapper
Author: Joost Sijm
Author-email: joostsijm@gmail.com
License: UNKNOWN
Platform: UNKNOWN
Classifier: Programming Language :: Python :: 3
Classifier: License :: OSI Approved :: Apache Software License
Classifier: Operating System :: OS Independent
License-File: LICENSE
Requires-Dist: appdirs
Requires-Dist: beautifulsoup4
Requires-Dist: cfscrape
Requires-Dist: python-dateutil
Requires-Dist: pathlib2
Requires-Dist: requests
Requires-Dist: selenium-stealth
Requires-Dist: webbot
Requires-Dist: python-anticaptcha
